{
  "pageTitle": "Contact",
  "pageDescription": "Get in touch with Holtzweb. Server, website, networking, or just a conversation. Let's talk about your infrastructure.",
  "heading": "Ask Me Anything.",
  "subHeading": "I read every message — I'll read what you wrote and respond as soon as I lay eyes on it.",
  "contactMethods": [
    {
      "iconKey": "phone",
      "label": "Call or text",
      "note": "Mon–Sun 7am–9pm"
    },
    {
      "iconKey": "envelope",
      "label": "Email",
      "note": "Typically responds within a few hours"
    }
  ],
  "form": {
    "heading": "What's going on?",
    "fields": {
      "name": { "label": "Name", "placeholder": "Your name or company" },
      "email": { "label": "Email", "placeholder": "you@company.com" },
      "message": { "label": "Message", "placeholder": "Tell me what's going on. The more detail the better — I actually read these." }
    },
    "submitLabel": "Send Message",
    "sendingLabel": "Sending…",
    "confirmationText": "You will get an email reply, affirming receipt.",
    "successMessage": "Message sent! We'll be in touch shortly.",
    "errorFallback": "Something went wrong. Please try again.",
    "networkError": "Network error. Check your connection and try again."
  }
}
