{
  "welcomeText": "Welcome to Holtzweb",
  "ctaText": "Contact Us Now",
  "navItems": [
    { "label": "Home", "href": "/", "iconKey": "home" },
    {
      "label": "Services",
      "href": "/services",
      "iconKey": "server",
      "children": [
        { "label": "WordPress & Web Dev", "href": "/services/wordpress-web-development", "iconKey": "wordpress" },
        { "label": "Linux Server Admin", "href": "/services/linux-server-administration", "iconKey": "terminal" },
        { "label": "Networking & Infrastructure", "href": "/services/networking-infrastructure", "iconKey": "network" },
        { "label": "Consulting & Support", "href": "/services/consulting-project-support", "iconKey": "support" }
      ]
    },
    { "label": "About", "href": "/about", "iconKey": "user" },
    {
      "label": "Blog",
      "href": "/blog",
      "iconKey": "book",
      "children": [
        { "label": "Posts", "href": "/blog", "iconKey": "book" },
        { "label": "Categories", "href": "/blog/categories", "iconKey": "grid" },
        { "label": "Timeline", "href": "/blog/timeline", "iconKey": "clock" }
      ]
    },
    { "label": "Projects", "href": "/projects", "iconKey": "monitor" },
    { "label": "Contact", "href": "/contact", "iconKey": "mail" }
  ],
  "sidebarSocialLabel": "Social",
  "sidebarOtherSitesLabel": "Other Sites",
  "otherSites": [
    { "label": "marcusholtz.com", "href": "https://marcusholtz.com", "iconKey": "user-outline" },
    { "label": "holtzhost.com",   "href": "https://holtzhost.com",   "iconKey": "home-outline" }
  ],
  "footerTagline": "Contact Us - Voice or Message",
  "footerLinks": {
    "Services": [
      { "label": "WordPress & Web Dev", "href": "/services/wordpress-web-development" },
      { "label": "Linux Server Admin", "href": "/services/linux-server-administration" },
      { "label": "Networking & Infrastructure", "href": "/services/networking-infrastructure" },
      { "label": "Consulting & Support", "href": "/services/consulting-project-support" }
    ],
    "Company": [
      { "label": "About Us", "href": "/about" },
      { "label": "Blog", "href": "/blog" },
      { "label": "Projects", "href": "/projects" },
      { "label": "Contact", "href": "/contact" }
    ],
    "Legal": [
      { "label": "Privacy Policy", "href": "/privacy" },
      { "label": "Terms of Service", "href": "/terms" }
    ]
  }
}
